beanstalktop.py
beanstalktop-0.1.0.dist-info/METADATA
beanstalktop-0.1.0.dist-info/RECORD
beanstalktop-0.1.0.dist-info/WHEEL
beanstalktop-0.1.0.dist-info/entry_points.txt
beanstalktop-0.1.0.dist-info/top_level.txt
