Metadata-Version: 2.1
Name: beanstalktop
Version: 0.1.0
Summary: A simple, top-like monitoring tool for beanstalkd
Home-page: https://github.com/OldhamMade/beanstalktop
Author: Phillip B Oldham
Author-email: UNKNOWN
License: MIT
Platform: UNKNOWN
Requires-Dist: beanstalkc
Requires-Dist: PyYAML
